django_uf_request
